[{"osmid":"https:\/\/www.openstreetmap.org\/way\/229421530","distance":7.15,"loc":"Point(10.719732 53.8055429)","tag":"taxiway"},{"osmid":"https:\/\/www.openstreetmap.org\/way\/229421529","distance":7.245,"loc":"Point(10.7020031 53.8020901)","tag":"taxiway"},{"osmid":"https:\/\/www.openstreetmap.org\/way\/229421531","distance":7.256,"loc":"Point(10.7021025 53.8019943)","tag":"taxiway"},{"osmid":"https:\/\/www.openstreetmap.org\/way\/302296439","distance":3.919,"loc":"Point(10.7050763 53.8333011)","tag":"helipad"}]